fa.v
module full_adder_gate(input A, B, Cin, output S, Cout);
  wire w1, w2, w3, w4;
  xor (w1, A, B);
  xor (S, w1, Cin);
  and (w2, A, B);
  and (w3, B, Cin);
  and (w4, Cin, A);
  or   (Cout, w2, w3, w4);
  
endmodule

fa_tb.v
module test_full_adder_gate;
  reg A, B, Cin;
  wire S, Cout;
  full_adder_gate uut (.A(A), .B(B), .Cin(Cin), .S(S), .Cout(Cout));
  initial begin;
$dumpfile("full_adder_gate.vcd");
        $dumpvars(0, test_full_adder_gate);

        $display("A B Cin | S Cout");
        $display("-----------------");
        $monitor("%b %b %b | %b %b", A, B, Cin, S, Cout);
    
        A = 0; B = 0; Cin = 0; #10
        A = 0; B = 0; Cin = 1; #10
        A = 0; B = 1; Cin = 0; #10
        A = 0; B = 1; Cin = 1; #10
        A = 1; B = 0; Cin = 0; #10
        A = 1; B = 0; Cin = 1; #10
        A = 1; B = 1; Cin = 0; #10
        A = 1; B = 1; Cin = 1; #10
    
        $finish;
    end 
endmodule

full_adder_gate.vcd
$date
	Fri Jul 04 06:26:27 2025
$end
$version
	Icarus Verilog
$end
$timescale
	1s
$end
$scope module test_full_adder_gate $end
$var wire 1 ! S $end
$var wire 1 " Cout $end
$var reg 1 # A $end
$var reg 1 $ B $end
$var reg 1 % Cin $end
$scope module uut $end
$var wire 1 # A $end
$var wire 1 $ B $end
$var wire 1 % Cin $end
$var wire 1 " Cout $end
$var wire 1 ! S $end
$var wire 1 & w1 $end
$var wire 1 ' w2 $end
$var wire 1 ( w3 $end
$var wire 1 ) w4 $end
$upscope $end
$upscope $end
$enddefinitions $end
#0
$dumpvars
0)
0(
0'
0&
0%
0$
0#
0"
0!
$end
#10
1!
1%
#20
1&
0%
1$
#30
1"
0!
1(
1%
#40
0"
1!
0(
0%
0$
1#
#50
1"
0!
1)
1%
#60
0)
0&
1'
0%
1$
#70
1!
1(
1)
1%
